mcp_server_rash/__init__.py
mcp_server_rash/main.py
mcp_server_rash/server.py
mcp_server_rash-0.1.0.dist-info/METADATA
mcp_server_rash-0.1.0.dist-info/WHEEL
mcp_server_rash-0.1.0.dist-info/entry_points.txt
mcp_server_rash-0.1.0.dist-info/licenses/LICENSE
mcp_server_rash-0.1.0.dist-info/RECORD
