Metadata-Version: 2.4
Name: mcp-server-rash
Version: 0.1.0
Summary: MCP server rash
License-Expression: Apache-2.0
License-File: LICENSE
Requires-Python: >=3.10
Requires-Dist: mcp[cli]>=1.3.0
Requires-Dist: requests>=2.32.3
Requires-Dist: twine>=6.1.0
